<?xml version="1.0" encoding="UTF-8"?>
<plantas>
  <planta>
    <codigo>2</codigo>
    <nombre>Tulipán</nombre>
    <foto>tulipan.jpg</foto>
    <descripcion>Flor colorida originaria de los Países Bajos.</descripcion>
  </planta>
  <planta>
    <codigo>3</codigo>
    <nombre>Cactus</nombre>
    <foto>cactus.jpg</foto>
    <descripcion>Planta resistente de zonas áridas.</descripcion>
  </planta>
  <planta>
    <codigo>4</codigo>
    <nombre>Girasol</nombre>
    <foto>girasol.jpg</foto>
    <descripcion>Planta alta con grandes flores amarillas.</descripcion>
  </planta>
  <planta>
    <codigo>5</codigo>
    <nombre>Lavanda</nombre>
    <foto>margarita.jpg</foto>
    <descripcion>Flor blanca con centro amarillo.</descripcion>
  </planta>
  <planta>
    <codigo>1</codigo>
    <nombre>Rosa</nombre>
    <foto>rosa.jpg</foto>
    <descripcion>Flor roja muy común en jardines.</descripcion>
  </planta>
  <planta>
    <codigo>6</codigo>
    <nombre>Tulipan</nombre>
    <foto>tulipan.jpg</foto>
    <descripcion>flor blanca</descripcion>
  </planta>
  <planta>
    <codigo>7</codigo>
    <nombre>Amapola</nombre>
    <foto>amapola.jpg</foto>
    <descripcion>flor naranja</descripcion>
  </planta>
</plantas>
